LICENSE
MANIFEST.in
README
setup.py
chiki_sms/CCPRestSDK.py
chiki_sms/__init__.py
chiki_sms/send.py
chiki_sms/xmltojson.py
chiki_sms.egg-info/PKG-INFO
chiki_sms.egg-info/SOURCES.txt
chiki_sms.egg-info/dependency_links.txt
chiki_sms.egg-info/not-zip-safe
chiki_sms.egg-info/requires.txt
chiki_sms.egg-info/top_level.txt