Metadata-Version: 1.0
Name: chiki-sms
Version: 0.0.1
Summary: chiki sms libs.
Home-page: https://github.com/endsh/chiki-sms
Author: Linshao
Author-email: 438985635@qq.com
License: UNKNOWN
Platform: any
